[
   {
      "Number": 5792,
      "OpenedBy": "boussaffawalid",
      "CreatedAt": "2021-06-07T14:47:55Z",
      "Recipe": "openjdk",
      "Change": 0,
      "ReviewURL": "https://github.com/conan-io/conan-center-index/pull/5792",
      "LastCommitSHA": "9e093ced819bd7f6a765629a3dd46269e1b3cbaf",
      "LastCommitAt": "2021-09-27T15:00:45Z",
      "CciBotPassed": true,
      "Summary": {
         "Count": 29,
         "ValidApprovals": 2,
         "TeamApproval": true,
         "Approvals": [
            "prince-chrismc",
            "jgsogo"
         ],
         "Blockers": null,
         "LastReview": {
            "ReviewerName": "jgsogo",
            "SubmittedAt": "2021-09-29T09:44:38Z",
            "HTMLURL": "https://github.com/conan-io/conan-center-index/pull/5792#pullrequestreview-766449256"
         }
      }
   },
   {
      "Number": 6771,
      "OpenedBy": "dvetutnev",
      "CreatedAt": "2021-08-09T01:57:29Z",
      "Recipe": "mariadb-connector-c",
      "Change": 1,
      "ReviewURL": "https://github.com/conan-io/conan-center-index/pull/6771",
      "LastCommitSHA": "72bf14eedd6bf994b7599fcbd1f0c238c2edf978",
      "LastCommitAt": "2021-08-09T09:16:46Z",
      "CciBotPassed": true,
      "Summary": {
         "Count": 2,
         "ValidApprovals": 2,
         "TeamApproval": true,
         "Approvals": [
            "SSE4",
            "ericLemanissier"
         ],
         "Blockers": null,
         "LastReview": {
            "ReviewerName": "ericLemanissier",
            "SubmittedAt": "2021-09-29T16:24:38Z",
            "HTMLURL": "https://github.com/conan-io/conan-center-index/pull/6771#pullrequestreview-766920916"
         }
      }
   },
   {
      "Number": 6805,
      "OpenedBy": "erikzenker",
      "CreatedAt": "2021-08-10T20:04:07Z",
      "Recipe": "hsm",
      "Change": 0,
      "ReviewURL": "https://github.com/conan-io/conan-center-index/pull/6805",
      "LastCommitSHA": "11a1b2fee18fc360b4b8f84e56eeb3772c56dbcd",
      "LastCommitAt": "2021-09-26T14:41:31Z",
      "CciBotPassed": true,
      "Summary": {
         "Count": 27,
         "ValidApprovals": 1,
         "TeamApproval": true,
         "Approvals": [
            "SSE4"
         ],
         "Blockers": null,
         "LastReview": {
            "ReviewerName": "prince-chrismc",
            "SubmittedAt": "2021-09-28T14:04:46Z",
            "HTMLURL": "https://github.com/conan-io/conan-center-index/pull/6805#pullrequestreview-765495371"
         }
      }
   },
   {
      "Number": 7075,
      "OpenedBy": "ericLemanissier",
      "CreatedAt": "2021-08-27T11:38:01Z",
      "Recipe": "sdl_image",
      "Change": 0,
      "ReviewURL": "https://github.com/conan-io/conan-center-index/pull/7075",
      "LastCommitSHA": "4cb1f77dcadf3b131356d60c688df2f9d4919b49",
      "LastCommitAt": "2021-09-27T14:17:06Z",
      "CciBotPassed": true,
      "Summary": {
         "Count": 5,
         "ValidApprovals": 2,
         "TeamApproval": true,
         "Approvals": [
            "prince-chrismc",
            "SSE4"
         ],
         "Blockers": null,
         "LastReview": {
            "ReviewerName": "SSE4",
            "SubmittedAt": "2021-09-28T18:20:42Z",
            "HTMLURL": "https://github.com/conan-io/conan-center-index/pull/7075#pullrequestreview-765810807"
         }
      }
   },
   {
      "Number": 7212,
      "OpenedBy": "madebr",
      "CreatedAt": "2021-09-08T16:43:48Z",
      "Recipe": "nspr",
      "Change": 1,
      "ReviewURL": "https://github.com/conan-io/conan-center-index/pull/7212",
      "LastCommitSHA": "3b05267ce8a18bb1c6c27c7c364fea341faa244c",
      "LastCommitAt": "2021-09-08T22:27:22Z",
      "CciBotPassed": false,
      "Summary": {
         "Count": 3,
         "ValidApprovals": 1,
         "TeamApproval": false,
         "Approvals": [
            "prince-chrismc"
         ],
         "Blockers": null,
         "LastReview": {
            "ReviewerName": "uilianries",
            "SubmittedAt": "2021-09-22T13:56:43Z",
            "HTMLURL": "https://github.com/conan-io/conan-center-index/pull/7212#pullrequestreview-760952960"
         }
      }
   },
   {
      "Number": 7296,
      "OpenedBy": "samuel-emrys",
      "CreatedAt": "2021-09-15T15:16:32Z",
      "Recipe": "openblas",
      "Change": 1,
      "ReviewURL": "https://github.com/conan-io/conan-center-index/pull/7296",
      "LastCommitSHA": "d0942f9fb6b5e37d33e2161e1206100237edf192",
      "LastCommitAt": "2021-09-20T13:29:51Z",
      "CciBotPassed": true,
      "Summary": {
         "Count": 3,
         "ValidApprovals": 2,
         "TeamApproval": true,
         "Approvals": [
            "prince-chrismc",
            "uilianries"
         ],
         "Blockers": null,
         "LastReview": {
            "ReviewerName": "uilianries",
            "SubmittedAt": "2021-09-29T13:39:41Z",
            "HTMLURL": "https://github.com/conan-io/conan-center-index/pull/7296#pullrequestreview-766699472"
         }
      }
   },
   {
      "Number": 7400,
      "OpenedBy": "coryan",
      "CreatedAt": "2021-09-23T16:03:22Z",
      "Recipe": "functions-framework-cpp",
      "Change": 0,
      "ReviewURL": "https://github.com/conan-io/conan-center-index/pull/7400",
      "LastCommitSHA": "301be9118f4967f5e1b45b4d4fa16f8d2c2dac9d",
      "LastCommitAt": "2021-09-28T17:10:35Z",
      "CciBotPassed": true,
      "Summary": {
         "Count": 15,
         "ValidApprovals": 2,
         "TeamApproval": true,
         "Approvals": [
            "SSE4",
            "prince-chrismc"
         ],
         "Blockers": null,
         "LastReview": {
            "ReviewerName": "prince-chrismc",
            "SubmittedAt": "2021-09-29T02:33:39Z",
            "HTMLURL": "https://github.com/conan-io/conan-center-index/pull/7400#pullrequestreview-766146752"
         }
      }
   },
   {
      "Number": 7402,
      "OpenedBy": "madebr",
      "CreatedAt": "2021-09-23T19:30:57Z",
      "Recipe": "fontconfig",
      "Change": 1,
      "ReviewURL": "https://github.com/conan-io/conan-center-index/pull/7402",
      "LastCommitSHA": "f05eb60f629657aa7f21c03b2108a1de4b00554c",
      "LastCommitAt": "2021-09-27T15:54:59Z",
      "CciBotPassed": true,
      "Summary": {
         "Count": 5,
         "ValidApprovals": 2,
         "TeamApproval": true,
         "Approvals": [
            "SSE4",
            "prince-chrismc"
         ],
         "Blockers": null,
         "LastReview": {
            "ReviewerName": "prince-chrismc",
            "SubmittedAt": "2021-09-29T02:35:49Z",
            "HTMLURL": "https://github.com/conan-io/conan-center-index/pull/7402#pullrequestreview-766147580"
         }
      }
   },
   {
      "Number": 7457,
      "OpenedBy": "ericLemanissier",
      "CreatedAt": "2021-09-29T06:12:39Z",
      "Recipe": "meson",
      "Change": 1,
      "ReviewURL": "https://github.com/conan-io/conan-center-index/pull/7457",
      "LastCommitSHA": "0e327048d3f1e28e1ab6d4b1b2726c4e95693380",
      "LastCommitAt": "2021-09-29T06:11:47Z",
      "CciBotPassed": true,
      "Summary": {
         "Count": 2,
         "ValidApprovals": 2,
         "TeamApproval": true,
         "Approvals": [
            "SSE4",
            "Croydon"
         ],
         "Blockers": null,
         "LastReview": {
            "ReviewerName": "Croydon",
            "SubmittedAt": "2021-09-29T16:04:57Z",
            "HTMLURL": "https://github.com/conan-io/conan-center-index/pull/7457#pullrequestreview-766905468"
         }
      }
   },
   {
      "Number": 7458,
      "OpenedBy": "toge",
      "CreatedAt": "2021-09-29T09:47:14Z",
      "Recipe": "aws-c-cal",
      "Change": 1,
      "ReviewURL": "https://github.com/conan-io/conan-center-index/pull/7458",
      "LastCommitSHA": "f3b2cf2a5b2bf2ea79c73b2c9b8ac809a1ac7a0a",
      "LastCommitAt": "2021-09-29T09:44:56Z",
      "CciBotPassed": true,
      "Summary": {
         "Count": 1,
         "ValidApprovals": 1,
         "TeamApproval": false,
         "Approvals": [
            "ericLemanissier"
         ],
         "Blockers": null,
         "LastReview": {
            "ReviewerName": "ericLemanissier",
            "SubmittedAt": "2021-09-29T16:12:30Z",
            "HTMLURL": "https://github.com/conan-io/conan-center-index/pull/7458#pullrequestreview-766914305"
         }
      }
   },
   {
      "Number": 7462,
      "OpenedBy": "ngrodzitski",
      "CreatedAt": "2021-09-29T19:02:07Z",
      "Recipe": "logr",
      "Change": 1,
      "ReviewURL": "https://github.com/conan-io/conan-center-index/pull/7462",
      "LastCommitSHA": "92cfe8a70f45192d9e8b2701576194b20ae50882",
      "LastCommitAt": "2021-09-29T18:59:19Z",
      "CciBotPassed": false,
      "Summary": {
         "Count": 0,
         "ValidApprovals": 0,
         "TeamApproval": false,
         "Approvals": null,
         "Blockers": null
      }
   }
]