[
   {
      "Number": 10939,
      "OpenedBy": "Sil3ntStorm",
      "CreatedAt": "2022-05-24T17:12:40Z",
      "Recipe": "openssl",
      "Change": 1,
      "ReviewURL": "https://github.com/conan-io/conan-center-index/pull/10939",
      "LastCommitSHA": "e2b65ee1a8db25b563ad5930e504f402c4528fc7",
      "LastCommitAt": "2022-07-21T10:35:48Z",
      "CciBotPassed": true,
      "Summary": {
         "Count": 0,
         "ValidApprovals": 0,
         "TeamApproval": false,
         "Approvals": null,
         "Blockers": null
      }
   },
   {
      "Number": 11725,
      "OpenedBy": "tsondergaard",
      "CreatedAt": "2022-07-16T13:14:11Z",
      "Recipe": "openssl",
      "Change": 1,
      "ReviewURL": "https://github.com/conan-io/conan-center-index/pull/11725",
      "LastCommitSHA": "d3c3659408eb9b65820a5c9215716bdb492cb760",
      "LastCommitAt": "2022-07-16T13:50:54Z",
      "CciBotPassed": true,
      "Summary": {
         "Count": 0,
         "ValidApprovals": 0,
         "TeamApproval": false,
         "Approvals": null,
         "Blockers": null
      }
   },
   {
      "Number": 12333,
      "OpenedBy": "willadsen",
      "CreatedAt": "2022-08-18T09:50:05Z",
      "Recipe": "foonathan-memory",
      "Change": 1,
      "ReviewURL": "https://github.com/conan-io/conan-center-index/pull/12333",
      "LastCommitSHA": "131ca31245100270caa5ef808d88944cfaaa609c",
      "LastCommitAt": "2022-09-01T09:13:27Z",
      "CciBotPassed": true,
      "Summary": {
         "Count": 3,
         "ValidApprovals": 1,
         "TeamApproval": true,
         "Approvals": [
            "SSE4"
         ],
         "Blockers": null,
         "LastReview": {
            "ReviewerName": "SSE4",
            "SubmittedAt": "2022-10-15T13:13:20Z",
            "HTMLURL": "https://github.com/conan-io/conan-center-index/pull/12333#pullrequestreview-1143186518"
         }
      }
   },
   {
      "Number": 12360,
      "OpenedBy": "szmyd",
      "CreatedAt": "2022-08-18T16:46:23Z",
      "Recipe": "nuraft",
      "Change": 0,
      "ReviewURL": "https://github.com/conan-io/conan-center-index/pull/12360",
      "LastCommitSHA": "872ea8a3132b1061e02fcbcea4735418410ec6c1",
      "LastCommitAt": "2022-09-15T09:56:23Z",
      "CciBotPassed": true,
      "Summary": {
         "Count": 18,
         "ValidApprovals": 1,
         "TeamApproval": true,
         "Approvals": [
            "SSE4"
         ],
         "Blockers": null,
         "LastReview": {
            "ReviewerName": "prince-chrismc",
            "SubmittedAt": "2022-10-17T20:28:40Z",
            "HTMLURL": "https://github.com/conan-io/conan-center-index/pull/12360#pullrequestreview-1144770684"
         }
      }
   },
   {
      "Number": 12844,
      "OpenedBy": "kissandras",
      "CreatedAt": "2022-09-06T06:47:58Z",
      "Recipe": "archicad-apidevkit",
      "Change": 0,
      "ReviewURL": "https://github.com/conan-io/conan-center-index/pull/12844",
      "LastCommitSHA": "ba628811e2f245a284cc8b6cb5a26a9b40dc51b1",
      "LastCommitAt": "2022-10-24T05:27:34Z",
      "CciBotPassed": true,
      "Summary": {
         "Count": 4,
         "ValidApprovals": 0,
         "TeamApproval": false,
         "Approvals": null,
         "Blockers": null,
         "LastReview": {
            "ReviewerName": "prince-chrismc",
            "SubmittedAt": "2022-10-22T04:03:02Z",
            "HTMLURL": "https://github.com/conan-io/conan-center-index/pull/12844#pullrequestreview-1151755619"
         }
      }
   },
   {
      "Number": 12896,
      "OpenedBy": "jellespijker",
      "CreatedAt": "2022-09-11T13:06:28Z",
      "Recipe": "autoconf",
      "Change": 1,
      "ReviewURL": "https://github.com/conan-io/conan-center-index/pull/12896",
      "LastCommitSHA": "afa1246f7aadd25bfa43018f564a597a609da36f",
      "LastCommitAt": "2022-10-23T08:05:21Z",
      "CciBotPassed": true,
      "Summary": {
         "Count": 19,
         "ValidApprovals": 1,
         "TeamApproval": false,
         "Approvals": [
            "jwillikers"
         ],
         "Blockers": [
            "uilianries"
         ],
         "LastReview": {
            "ReviewerName": "uilianries",
            "SubmittedAt": "2022-10-24T11:36:26Z",
            "HTMLURL": "https://github.com/conan-io/conan-center-index/pull/12896#pullrequestreview-1152942416"
         }
      }
   },
   {
      "Number": 13068,
      "OpenedBy": "fpelliccioni",
      "CreatedAt": "2022-09-22T07:06:29Z",
      "Recipe": "cppfront",
      "Change": 0,
      "ReviewURL": "https://github.com/conan-io/conan-center-index/pull/13068",
      "LastCommitSHA": "8857ab142b6fb7a8b895a4f237e75eddf45eb3cf",
      "LastCommitAt": "2022-10-24T08:18:20Z",
      "CciBotPassed": false,
      "Summary": {
         "Count": 16,
         "ValidApprovals": 0,
         "TeamApproval": false,
         "Approvals": null,
         "Blockers": null,
         "LastReview": {
            "ReviewerName": "prince-chrismc",
            "SubmittedAt": "2022-10-22T03:50:39Z",
            "HTMLURL": "https://github.com/conan-io/conan-center-index/pull/13068#pullrequestreview-1151753973"
         }
      }
   },
   {
      "Number": 13169,
      "OpenedBy": "ggulgulia",
      "CreatedAt": "2022-09-27T06:13:20Z",
      "Recipe": "openblas",
      "Change": 1,
      "ReviewURL": "https://github.com/conan-io/conan-center-index/pull/13169",
      "LastCommitSHA": "24bd4ca40ccab4648e417c071ab958801b541031",
      "LastCommitAt": "2022-09-27T15:35:43Z",
      "CciBotPassed": false,
      "Summary": {
         "Count": 2,
         "ValidApprovals": 0,
         "TeamApproval": false,
         "Approvals": null,
         "Blockers": null,
         "LastReview": {
            "ReviewerName": "uilianries",
            "SubmittedAt": "2022-09-27T14:11:13Z",
            "HTMLURL": "https://github.com/conan-io/conan-center-index/pull/13169#pullrequestreview-1122075340"
         }
      }
   },
   {
      "Number": 13205,
      "OpenedBy": "syoliver",
      "CreatedAt": "2022-09-28T20:37:27Z",
      "Recipe": "hyperscan",
      "Change": 1,
      "ReviewURL": "https://github.com/conan-io/conan-center-index/pull/13205",
      "LastCommitSHA": "bcb13631c96d8e93741fdc5e057d9c8ad62248e2",
      "LastCommitAt": "2022-09-28T20:02:54Z",
      "CciBotPassed": true,
      "Summary": {
         "Count": 3,
         "ValidApprovals": 1,
         "TeamApproval": false,
         "Approvals": [
            "jwillikers"
         ],
         "Blockers": null,
         "LastReview": {
            "ReviewerName": "uilianries",
            "SubmittedAt": "2022-10-18T09:25:33Z",
            "HTMLURL": "https://github.com/conan-io/conan-center-index/pull/13205#pullrequestreview-1145422371"
         }
      }
   },
   {
      "Number": 13355,
      "OpenedBy": "jwillikers",
      "CreatedAt": "2022-10-07T20:37:46Z",
      "Recipe": "libffi",
      "Change": 1,
      "ReviewURL": "https://github.com/conan-io/conan-center-index/pull/13355",
      "LastCommitSHA": "9eb26830471cbb4ad81f59251a52194cf4ef2b40",
      "LastCommitAt": "2022-10-24T02:52:53Z",
      "CciBotPassed": true,
      "Summary": {
         "Count": 5,
         "ValidApprovals": 1,
         "TeamApproval": true,
         "Approvals": [
            "uilianries"
         ],
         "Blockers": null,
         "LastReview": {
            "ReviewerName": "uilianries",
            "SubmittedAt": "2022-10-24T14:31:42Z",
            "HTMLURL": "https://github.com/conan-io/conan-center-index/pull/13355#pullrequestreview-1153250770"
         }
      }
   },
   {
      "Number": 13358,
      "OpenedBy": "toge",
      "CreatedAt": "2022-10-08T05:41:03Z",
      "Recipe": "libcpuid",
      "Change": 1,
      "ReviewURL": "https://github.com/conan-io/conan-center-index/pull/13358",
      "LastCommitSHA": "4bfbd53a542f52be5e4ea200512a056dd8b6361d",
      "LastCommitAt": "2022-10-24T09:25:10Z",
      "CciBotPassed": false,
      "Summary": {
         "Count": 5,
         "ValidApprovals": 1,
         "TeamApproval": false,
         "Approvals": [
            "jwillikers"
         ],
         "Blockers": null,
         "LastReview": {
            "ReviewerName": "jwillikers",
            "SubmittedAt": "2022-10-24T10:57:52Z",
            "HTMLURL": "https://github.com/conan-io/conan-center-index/pull/13358#pullrequestreview-1152952996"
         }
      }
   },
   {
      "Number": 13552,
      "OpenedBy": "Nekto89",
      "CreatedAt": "2022-10-17T15:20:42Z",
      "Recipe": "onetbb",
      "Change": 1,
      "ReviewURL": "https://github.com/conan-io/conan-center-index/pull/13552",
      "LastCommitSHA": "791784e89f89dacdc384c07a97b22de145efd849",
      "LastCommitAt": "2022-10-17T15:18:37Z",
      "CciBotPassed": true,
      "Summary": {
         "Count": 2,
         "ValidApprovals": 1,
         "TeamApproval": true,
         "Approvals": [
            "prince-chrismc"
         ],
         "Blockers": null,
         "LastReview": {
            "ReviewerName": "uilianries",
            "SubmittedAt": "2022-10-18T09:03:30Z",
            "HTMLURL": "https://github.com/conan-io/conan-center-index/pull/13552#pullrequestreview-1145386699"
         }
      }
   },
   {
      "Number": 13586,
      "OpenedBy": "datalogics-kam",
      "CreatedAt": "2022-10-18T17:53:10Z",
      "Recipe": "innoextract",
      "Change": 1,
      "ReviewURL": "https://github.com/conan-io/conan-center-index/pull/13586",
      "LastCommitSHA": "dc5a2607906e45415afd8e7739818ab97cda181b",
      "LastCommitAt": "2022-10-18T17:48:46Z",
      "CciBotPassed": true,
      "Summary": {
         "Count": 2,
         "ValidApprovals": 2,
         "TeamApproval": true,
         "Approvals": [
            "uilianries",
            "jwillikers"
         ],
         "Blockers": null,
         "LastReview": {
            "ReviewerName": "jwillikers",
            "SubmittedAt": "2022-10-19T18:56:26Z",
            "HTMLURL": "https://github.com/conan-io/conan-center-index/pull/13586#pullrequestreview-1148123884"
         }
      }
   },
   {
      "Number": 13614,
      "OpenedBy": "madebr",
      "CreatedAt": "2022-10-19T21:21:45Z",
      "Recipe": "yder",
      "Change": 0,
      "ReviewURL": "https://github.com/conan-io/conan-center-index/pull/13614",
      "LastCommitSHA": "a2b7bb03f54edb3808217d21db698cecc9f6fc5f",
      "LastCommitAt": "2022-10-19T21:20:33Z",
      "CciBotPassed": true,
      "Summary": {
         "Count": 3,
         "ValidApprovals": 1,
         "TeamApproval": false,
         "Approvals": [
            "jwillikers"
         ],
         "Blockers": null,
         "LastReview": {
            "ReviewerName": "prince-chrismc",
            "SubmittedAt": "2022-10-24T02:39:42Z",
            "HTMLURL": "https://github.com/conan-io/conan-center-index/pull/13614#pullrequestreview-1152479039"
         }
      }
   },
   {
      "Number": 13621,
      "OpenedBy": "kexianda",
      "CreatedAt": "2022-10-20T03:58:15Z",
      "Recipe": "folly",
      "Change": 1,
      "ReviewURL": "https://github.com/conan-io/conan-center-index/pull/13621",
      "LastCommitSHA": "4fa53b8f7e18e780c761f31ca13f0eeac86a71ca",
      "LastCommitAt": "2022-10-24T10:19:18Z",
      "CciBotPassed": true,
      "Summary": {
         "Count": 6,
         "ValidApprovals": 1,
         "TeamApproval": false,
         "Approvals": [
            "jwillikers"
         ],
         "Blockers": null,
         "LastReview": {
            "ReviewerName": "jwillikers",
            "SubmittedAt": "2022-10-24T11:13:22Z",
            "HTMLURL": "https://github.com/conan-io/conan-center-index/pull/13621#pullrequestreview-1152970111"
         }
      }
   },
   {
      "Number": 13628,
      "OpenedBy": "theirix",
      "CreatedAt": "2022-10-20T12:14:53Z",
      "Recipe": "libnghttp2",
      "Change": 1,
      "ReviewURL": "https://github.com/conan-io/conan-center-index/pull/13628",
      "LastCommitSHA": "9c1837875969f006e9ae14040a6aba0c396670cc",
      "LastCommitAt": "2022-10-24T11:51:27Z",
      "CciBotPassed": false,
      "Summary": {
         "Count": 4,
         "ValidApprovals": 1,
         "TeamApproval": false,
         "Approvals": [
            "jwillikers"
         ],
         "Blockers": null,
         "LastReview": {
            "ReviewerName": "jwillikers",
            "SubmittedAt": "2022-10-24T12:22:11Z",
            "HTMLURL": "https://github.com/conan-io/conan-center-index/pull/13628#pullrequestreview-1153047837"
         }
      }
   },
   {
      "Number": 13631,
      "OpenedBy": "theirix",
      "CreatedAt": "2022-10-20T13:23:34Z",
      "Recipe": "exiv2",
      "Change": 1,
      "ReviewURL": "https://github.com/conan-io/conan-center-index/pull/13631",
      "LastCommitSHA": "edea8a8c3863a937e3a2421684618c948bea4429",
      "LastCommitAt": "2022-10-24T09:39:35Z",
      "CciBotPassed": true,
      "Summary": {
         "Count": 2,
         "ValidApprovals": 0,
         "TeamApproval": false,
         "Approvals": null,
         "Blockers": null,
         "LastReview": {
            "ReviewerName": "uilianries",
            "SubmittedAt": "2022-10-21T13:06:19Z",
            "HTMLURL": "https://github.com/conan-io/conan-center-index/pull/13631#pullrequestreview-1150925364"
         }
      }
   },
   {
      "Number": 13635,
      "OpenedBy": "schoetbi",
      "CreatedAt": "2022-10-20T14:42:10Z",
      "Recipe": "flatbuffers",
      "Change": 1,
      "ReviewURL": "https://github.com/conan-io/conan-center-index/pull/13635",
      "LastCommitSHA": "a0447e9f2773df0e87c76b0f985e098066657f13",
      "LastCommitAt": "2022-10-20T14:34:35Z",
      "CciBotPassed": false,
      "Summary": {
         "Count": 0,
         "ValidApprovals": 0,
         "TeamApproval": false,
         "Approvals": null,
         "Blockers": null
      }
   },
   {
      "Number": 13638,
      "OpenedBy": "toge",
      "CreatedAt": "2022-10-20T16:07:01Z",
      "Recipe": "watcher",
      "Change": 0,
      "ReviewURL": "https://github.com/conan-io/conan-center-index/pull/13638",
      "LastCommitSHA": "2a3f45c863424c515b473704b67695838069774e",
      "LastCommitAt": "2022-10-24T13:53:55Z",
      "CciBotPassed": true,
      "Summary": {
         "Count": 1,
         "ValidApprovals": 0,
         "TeamApproval": false,
         "Approvals": null,
         "Blockers": null,
         "LastReview": {
            "ReviewerName": "uilianries",
            "SubmittedAt": "2022-10-21T14:06:21Z",
            "HTMLURL": "https://github.com/conan-io/conan-center-index/pull/13638#pullrequestreview-1151023469"
         }
      }
   },
   {
      "Number": 13645,
      "OpenedBy": "jwillikers",
      "CreatedAt": "2022-10-20T19:20:45Z",
      "Recipe": "glib",
      "Change": 1,
      "ReviewURL": "https://github.com/conan-io/conan-center-index/pull/13645",
      "LastCommitSHA": "9ec8b654283b28967169ca51e880ede0b617c7c6",
      "LastCommitAt": "2022-10-20T19:15:20Z",
      "CciBotPassed": true,
      "Summary": {
         "Count": 0,
         "ValidApprovals": 0,
         "TeamApproval": false,
         "Approvals": null,
         "Blockers": null
      }
   },
   {
      "Number": 13660,
      "OpenedBy": "toge",
      "CreatedAt": "2022-10-21T09:33:12Z",
      "Recipe": "lief",
      "Change": 1,
      "ReviewURL": "https://github.com/conan-io/conan-center-index/pull/13660",
      "LastCommitSHA": "af6d2ca3708c3b8303a50d96f93a79b34a17759c",
      "LastCommitAt": "2022-10-21T14:34:56Z",
      "CciBotPassed": true,
      "Summary": {
         "Count": 2,
         "ValidApprovals": 1,
         "TeamApproval": false,
         "Approvals": [
            "jwillikers"
         ],
         "Blockers": null,
         "LastReview": {
            "ReviewerName": "prince-chrismc",
            "SubmittedAt": "2022-10-24T02:46:21Z",
            "HTMLURL": "https://github.com/conan-io/conan-center-index/pull/13660#pullrequestreview-1152485540"
         }
      }
   },
   {
      "Number": 13662,
      "OpenedBy": "SpaceIm",
      "CreatedAt": "2022-10-21T12:19:15Z",
      "Recipe": "tensorpipe",
      "Change": 1,
      "ReviewURL": "https://github.com/conan-io/conan-center-index/pull/13662",
      "LastCommitSHA": "aa8c3b18a99767d68b73b1255e0b2387bf153927",
      "LastCommitAt": "2022-10-21T12:18:44Z",
      "CciBotPassed": true,
      "Summary": {
         "Count": 2,
         "ValidApprovals": 1,
         "TeamApproval": true,
         "Approvals": [
            "uilianries"
         ],
         "Blockers": null,
         "LastReview": {
            "ReviewerName": "prince-chrismc",
            "SubmittedAt": "2022-10-24T02:48:44Z",
            "HTMLURL": "https://github.com/conan-io/conan-center-index/pull/13662#pullrequestreview-1152486467"
         }
      }
   },
   {
      "Number": 13667,
      "OpenedBy": "jwillikers",
      "CreatedAt": "2022-10-21T13:38:52Z",
      "Recipe": "bzip2",
      "Change": 1,
      "ReviewURL": "https://github.com/conan-io/conan-center-index/pull/13667",
      "LastCommitSHA": "a245b5fae8f26f0ef3f777072ecf5b16e14635f0",
      "LastCommitAt": "2022-10-24T10:52:42Z",
      "CciBotPassed": true,
      "Summary": {
         "Count": 6,
         "ValidApprovals": 0,
         "TeamApproval": false,
         "Approvals": null,
         "Blockers": [
            "prince-chrismc"
         ],
         "LastReview": {
            "ReviewerName": "SpaceIm",
            "SubmittedAt": "2022-10-24T09:17:10Z",
            "HTMLURL": "https://github.com/conan-io/conan-center-index/pull/13667#pullrequestreview-1152815140"
         }
      }
   },
   {
      "Number": 13668,
      "OpenedBy": "jwillikers",
      "CreatedAt": "2022-10-21T17:14:16Z",
      "Recipe": "xkbcommon",
      "Change": 1,
      "ReviewURL": "https://github.com/conan-io/conan-center-index/pull/13668",
      "LastCommitSHA": "6c831280795fef8a1c0767e4b6f82c8214922dd0",
      "LastCommitAt": "2022-10-21T17:19:29Z",
      "CciBotPassed": true,
      "Summary": {
         "Count": 1,
         "ValidApprovals": 1,
         "TeamApproval": true,
         "Approvals": [
            "uilianries"
         ],
         "Blockers": null,
         "LastReview": {
            "ReviewerName": "uilianries",
            "SubmittedAt": "2022-10-24T09:30:38Z",
            "HTMLURL": "https://github.com/conan-io/conan-center-index/pull/13668#pullrequestreview-1152834040"
         }
      }
   },
   {
      "Number": 13674,
      "OpenedBy": "psyinf",
      "CreatedAt": "2022-10-21T21:49:54Z",
      "Recipe": "gmtl",
      "Change": 0,
      "ReviewURL": "https://github.com/conan-io/conan-center-index/pull/13674",
      "LastCommitSHA": "1cbab2fd6c2c903f0af76256d21adcc7ea5e788d",
      "LastCommitAt": "2022-10-24T12:03:36Z",
      "CciBotPassed": false,
      "Summary": {
         "Count": 4,
         "ValidApprovals": 0,
         "TeamApproval": false,
         "Approvals": null,
         "Blockers": null,
         "LastReview": {
            "ReviewerName": "uilianries",
            "SubmittedAt": "2022-10-24T11:57:40Z",
            "HTMLURL": "https://github.com/conan-io/conan-center-index/pull/13674#pullrequestreview-1153018556"
         }
      }
   },
   {
      "Number": 13684,
      "OpenedBy": "SpaceIm",
      "CreatedAt": "2022-10-22T13:26:06Z",
      "Recipe": "libcurl",
      "Change": 1,
      "ReviewURL": "https://github.com/conan-io/conan-center-index/pull/13684",
      "LastCommitSHA": "929496d95beb16dbe934eeed5f8af29606979d1b",
      "LastCommitAt": "2022-10-24T09:11:33Z",
      "CciBotPassed": false,
      "Summary": {
         "Count": 4,
         "ValidApprovals": 1,
         "TeamApproval": false,
         "Approvals": [
            "jwillikers"
         ],
         "Blockers": null,
         "LastReview": {
            "ReviewerName": "jwillikers",
            "SubmittedAt": "2022-10-24T10:56:37Z",
            "HTMLURL": "https://github.com/conan-io/conan-center-index/pull/13684#pullrequestreview-1152951604"
         }
      }
   },
   {
      "Number": 13691,
      "OpenedBy": "MartinDelille",
      "CreatedAt": "2022-10-23T01:41:11Z",
      "Recipe": "openapi-generator",
      "Change": 0,
      "ReviewURL": "https://github.com/conan-io/conan-center-index/pull/13691",
      "LastCommitSHA": "76fc20acdafc42d4f277d97389edd081266fda05",
      "LastCommitAt": "2022-10-23T10:07:59Z",
      "CciBotPassed": true,
      "Summary": {
         "Count": 5,
         "ValidApprovals": 1,
         "TeamApproval": false,
         "Approvals": [
            "jwillikers"
         ],
         "Blockers": null,
         "LastReview": {
            "ReviewerName": "jwillikers",
            "SubmittedAt": "2022-10-24T14:32:31Z",
            "HTMLURL": "https://github.com/conan-io/conan-center-index/pull/13691#pullrequestreview-1153252161"
         }
      }
   },
   {
      "Number": 13697,
      "OpenedBy": "SpaceIm",
      "CreatedAt": "2022-10-23T12:50:20Z",
      "Recipe": "opencl-icd-loader",
      "Change": 1,
      "ReviewURL": "https://github.com/conan-io/conan-center-index/pull/13697",
      "LastCommitSHA": "effd943138d938cd529c8295b880942f2b6acabe",
      "LastCommitAt": "2022-10-23T13:21:14Z",
      "CciBotPassed": true,
      "Summary": {
         "Count": 2,
         "ValidApprovals": 1,
         "TeamApproval": true,
         "Approvals": [
            "uilianries"
         ],
         "Blockers": null,
         "LastReview": {
            "ReviewerName": "jwillikers",
            "SubmittedAt": "2022-10-24T12:25:39Z",
            "HTMLURL": "https://github.com/conan-io/conan-center-index/pull/13697#pullrequestreview-1153051493"
         }
      }
   },
   {
      "Number": 13707,
      "OpenedBy": "SpaceIm",
      "CreatedAt": "2022-10-23T22:25:37Z",
      "Recipe": "blend2d",
      "Change": 1,
      "ReviewURL": "https://github.com/conan-io/conan-center-index/pull/13707",
      "LastCommitSHA": "09f84558f5652a19824a4596292f861782c2b0b9",
      "LastCommitAt": "2022-10-23T22:23:28Z",
      "CciBotPassed": true,
      "Summary": {
         "Count": 2,
         "ValidApprovals": 2,
         "TeamApproval": true,
         "Approvals": [
            "jwillikers",
            "uilianries"
         ],
         "Blockers": null,
         "LastReview": {
            "ReviewerName": "uilianries",
            "SubmittedAt": "2022-10-24T13:40:19Z",
            "HTMLURL": "https://github.com/conan-io/conan-center-index/pull/13707#pullrequestreview-1153161882"
         }
      }
   },
   {
      "Number": 13709,
      "OpenedBy": "SpaceIm",
      "CreatedAt": "2022-10-23T23:03:18Z",
      "Recipe": "cpputest",
      "Change": 1,
      "ReviewURL": "https://github.com/conan-io/conan-center-index/pull/13709",
      "LastCommitSHA": "3e1b0186b842416db27d2482d9b01ffa5cf0317e",
      "LastCommitAt": "2022-10-24T00:15:54Z",
      "CciBotPassed": true,
      "Summary": {
         "Count": 2,
         "ValidApprovals": 2,
         "TeamApproval": true,
         "Approvals": [
            "jwillikers",
            "uilianries"
         ],
         "Blockers": null,
         "LastReview": {
            "ReviewerName": "uilianries",
            "SubmittedAt": "2022-10-24T13:50:29Z",
            "HTMLURL": "https://github.com/conan-io/conan-center-index/pull/13709#pullrequestreview-1153178689"
         }
      }
   },
   {
      "Number": 13713,
      "OpenedBy": "toge",
      "CreatedAt": "2022-10-24T06:04:42Z",
      "Recipe": "civetweb",
      "Change": 1,
      "ReviewURL": "https://github.com/conan-io/conan-center-index/pull/13713",
      "LastCommitSHA": "f73eae642a54041d0852334e9c57740f9052bf26",
      "LastCommitAt": "2022-10-24T06:56:46Z",
      "CciBotPassed": true,
      "Summary": {
         "Count": 2,
         "ValidApprovals": 2,
         "TeamApproval": false,
         "Approvals": [
            "SpaceIm",
            "jwillikers"
         ],
         "Blockers": null,
         "LastReview": {
            "ReviewerName": "jwillikers",
            "SubmittedAt": "2022-10-24T11:00:21Z",
            "HTMLURL": "https://github.com/conan-io/conan-center-index/pull/13713#pullrequestreview-1152955624"
         }
      }
   },
   {
      "Number": 13714,
      "OpenedBy": "toge",
      "CreatedAt": "2022-10-24T08:35:08Z",
      "Recipe": "c-blosc2",
      "Change": 1,
      "ReviewURL": "https://github.com/conan-io/conan-center-index/pull/13714",
      "LastCommitSHA": "c1fc184f8f871b2774303fa9652775c1eec527fa",
      "LastCommitAt": "2022-10-24T08:33:44Z",
      "CciBotPassed": true,
      "Summary": {
         "Count": 1,
         "ValidApprovals": 1,
         "TeamApproval": false,
         "Approvals": [
            "jwillikers"
         ],
         "Blockers": null,
         "LastReview": {
            "ReviewerName": "jwillikers",
            "SubmittedAt": "2022-10-24T11:00:53Z",
            "HTMLURL": "https://github.com/conan-io/conan-center-index/pull/13714#pullrequestreview-1152956273"
         }
      }
   },
   {
      "Number": 13718,
      "OpenedBy": "conan-center-bot",
      "CreatedAt": "2022-10-24T11:38:08Z",
      "Recipe": ".c3i",
      "Change": 3,
      "ReviewURL": "https://github.com/conan-io/conan-center-index/pull/13718",
      "LastCommitSHA": "375d16b572d3cd4edbd052ecca06ebb3f54eadac",
      "LastCommitAt": "2022-10-24T11:38:05Z",
      "CciBotPassed": true,
      "Summary": {
         "Count": 1,
         "ValidApprovals": 1,
         "TeamApproval": false,
         "Approvals": [
            "jwillikers"
         ],
         "Blockers": null,
         "LastReview": {
            "ReviewerName": "jwillikers",
            "SubmittedAt": "2022-10-24T12:30:18Z",
            "HTMLURL": "https://github.com/conan-io/conan-center-index/pull/13718#pullrequestreview-1153058178"
         }
      }
   },
   {
      "Number": 13720,
      "OpenedBy": "SpaceIm",
      "CreatedAt": "2022-10-24T12:16:22Z",
      "Recipe": "tiny-aes-c",
      "Change": 1,
      "ReviewURL": "https://github.com/conan-io/conan-center-index/pull/13720",
      "LastCommitSHA": "a15b294d9e158da2d1f17d3a1c79986e07727d6f",
      "LastCommitAt": "2022-10-24T12:16:02Z",
      "CciBotPassed": true,
      "Summary": {
         "Count": 1,
         "ValidApprovals": 1,
         "TeamApproval": false,
         "Approvals": [
            "jwillikers"
         ],
         "Blockers": null,
         "LastReview": {
            "ReviewerName": "jwillikers",
            "SubmittedAt": "2022-10-24T12:31:54Z",
            "HTMLURL": "https://github.com/conan-io/conan-center-index/pull/13720#pullrequestreview-1153060192"
         }
      }
   },
   {
      "Number": 13721,
      "OpenedBy": "jwillikers",
      "CreatedAt": "2022-10-24T12:50:25Z",
      "Recipe": "eigen",
      "Change": 1,
      "ReviewURL": "https://github.com/conan-io/conan-center-index/pull/13721",
      "LastCommitSHA": "6e1d3754b80d643fe6663b5ec0ab043697fb69bc",
      "LastCommitAt": "2022-10-24T12:49:51Z",
      "CciBotPassed": false,
      "Summary": {
         "Count": 1,
         "ValidApprovals": 1,
         "TeamApproval": false,
         "Approvals": [
            "SpaceIm"
         ],
         "Blockers": null,
         "LastReview": {
            "ReviewerName": "SpaceIm",
            "SubmittedAt": "2022-10-24T12:59:32Z",
            "HTMLURL": "https://github.com/conan-io/conan-center-index/pull/13721#pullrequestreview-1153097809"
         }
      }
   },
   {
      "Number": 13725,
      "OpenedBy": "jwillikers",
      "CreatedAt": "2022-10-24T13:16:09Z",
      "Recipe": "ms-gsl",
      "Change": 1,
      "ReviewURL": "https://github.com/conan-io/conan-center-index/pull/13725",
      "LastCommitSHA": "e0cb55160a555240bb74fac3a60c7714ec5c3515",
      "LastCommitAt": "2022-10-24T13:15:42Z",
      "CciBotPassed": false,
      "Summary": {
         "Count": 0,
         "ValidApprovals": 0,
         "TeamApproval": false,
         "Approvals": null,
         "Blockers": null
      }
   },
   {
      "Number": 13726,
      "OpenedBy": "db4",
      "CreatedAt": "2022-10-24T13:28:32Z",
      "Recipe": "opencv",
      "Change": 1,
      "ReviewURL": "https://github.com/conan-io/conan-center-index/pull/13726",
      "LastCommitSHA": "697c19efb63512809a73322dab807c252893dbc2",
      "LastCommitAt": "2022-10-24T12:53:39Z",
      "CciBotPassed": false,
      "Summary": {
         "Count": 0,
         "ValidApprovals": 0,
         "TeamApproval": false,
         "Approvals": null,
         "Blockers": null
      }
   },
   {
      "Number": 13727,
      "OpenedBy": "jwillikers",
      "CreatedAt": "2022-10-24T13:41:09Z",
      "Recipe": "fmt",
      "Change": 1,
      "ReviewURL": "https://github.com/conan-io/conan-center-index/pull/13727",
      "LastCommitSHA": "a67681b8ad2bc69cda9686c5a4f8a0e5c5c6198c",
      "LastCommitAt": "2022-10-24T13:40:11Z",
      "CciBotPassed": false,
      "Summary": {
         "Count": 0,
         "ValidApprovals": 0,
         "TeamApproval": false,
         "Approvals": null,
         "Blockers": null
      }
   }
]